setup.py
pascha/__init__.py
pascha/computus.py
pascha/feasts.py
pascha/tests.py
pascha/traditions.py
pascha.egg-info/PKG-INFO
pascha.egg-info/SOURCES.txt
pascha.egg-info/dependency_links.txt
pascha.egg-info/top_level.txt
