Metadata-Version: 1.0
Name: pascha
Version: 0.4
Summary: Pascha (Easter) Computation Utility Library
Home-page: http://pypi.python.org/pypi/pascha/
Author: Rajiv Bakulesh Shah
Author-email: raj@enfoldsystems.com
License: UNKNOWN
Platform: UNKNOWN
Classifier: Development Status :: 3 - Alpha
Classifier: Intended Audience :: Developers
Classifier: Intended Audience :: Religion
Classifier: License :: OSI Approved :: BSD License
Classifier: Operating System :: OS Independent
Classifier: Programming Language :: Python
Classifier: Topic :: Religion
Classifier: Topic :: Software Development :: Libraries
Classifier: Topic :: Utilities
